README.md
pkg2ls.py
setup.py
pkg2ls.egg-info/PKG-INFO
pkg2ls.egg-info/SOURCES.txt
pkg2ls.egg-info/dependency_links.txt
pkg2ls.egg-info/top_level.txt